docs/knowledge/sci_results.py
docs/usage/basic.py
lfsir/__init__.py
lfsir/api.py
lfsir/maintainer.py
lfsir/config/settings.yaml
lfsir/knowledge_base/__init__.py
lfsir/knowledge_base/sci_results/T001.py
lfsir/knowledge_base/sci_results/__init__.py
lfsir/metadata/id_information.yaml
lfsir/metadata/raw_files.yaml
lfsir/metadata/schema.yaml
lfsir/metadata/tables.yaml
lfsir-0.6.1.dist-info/licenses/LICENCE
tests/test_by_results/results/test_results.py
lfsir-0.6.1.dist-info/METADATA
lfsir-0.6.1.dist-info/WHEEL
lfsir-0.6.1.dist-info/top_level.txt
lfsir-0.6.1.dist-info/RECORD
