Metadata-Version: 2.4
Name: lfsir
Version: 0.6.1
Author-email: Mohammad Amin Alavian <m.amin.alavian@gmail.com>
Project-URL: Homepage, https://github.com/Iran-Open-Data/LFSIR
Project-URL: Repository, https://github.com/Iran-Open-Data/LFSIR
Keywords: iran,survey,data,socioeconomic
Requires-Python: >=3.10
License-File: LICENCE
Requires-Dist: bssir
Provides-Extra: dev
Requires-Dist: bssir[dev]; extra == "dev"
Provides-Extra: maintain
Requires-Dist: bssir[maintain]; extra == "maintain"
Provides-Extra: notebook
Requires-Dist: bssir[notebook]; extra == "notebook"
Dynamic: license-file
